bentodev/__init__.py
bentodev/__version__.py
bentodev/cli.py
bentodev/core.py
bentodev/config/__init__.py
bentodev/config/settings.py
bentodev/setup_files/base_config.json
bentodev/setup_files/config.json
bentodev/templates/jinja2/macros/forms.html
bentodev/utils/__init__.py
bentodev/utils/command_functions.py
bentodev/utils/environment.py
bentodev/utils/factory.py
bentodev/utils/filters.py
bentodev/utils/functional.py
bentodev/utils/helpers.py
bentodev/utils/image_utils.py
bentodev/utils/paginator.py
bentodev/utils/safestring.py
bentodev/utils/server.py
bentodev/utils/text.py
bentodev/utils/translation.py
bentodev-2018.11.2.dist-info/METADATA
bentodev-2018.11.2.dist-info/WHEEL
bentodev-2018.11.2.dist-info/entry_points.txt
bentodev-2018.11.2.dist-info/top_level.txt
bentodev-2018.11.2.dist-info/RECORD
