Metadata-Version: 2.1
Name: bentodev
Version: 2018.11.2
Summary: BentoBox Local Development System
Home-page: https://github.com/getbento/bentodev
Author: Dylan Stein
Author-email: dylan@getbento.com
License: UNKNOWN
Keywords: bentobox bentodev
Platform: UNKNOWN
Classifier: Development Status :: 3 - Alpha
Classifier: Environment :: Console
Classifier: Intended Audience :: Developers
Classifier: Natural Language :: English
Classifier: Operating System :: POSIX
Classifier: Programming Language :: Python
Classifier: Programming Language :: Python :: 3.6
Classifier: Programming Language :: Python :: Implementation :: CPython
Classifier: Programming Language :: Python :: Implementation :: PyPy
Classifier: Topic :: Software Development :: Build Tools
Requires-Dist: Click (==6.7)
Requires-Dist: Flask (==0.12.1)
Requires-Dist: gitdb2 (==2.0.0)
Requires-Dist: GitPython (==2.1.3)
Requires-Dist: itsdangerous (==0.24)
Requires-Dist: Jinja2 (==2.9.6)
Requires-Dist: libsass (==0.12.3)
Requires-Dist: MarkupSafe (==1.0)
Requires-Dist: money (==1.3.0)
Requires-Dist: pip (==9.0.1)
Requires-Dist: python-dateutil (==2.6.0)
Requires-Dist: pytz (==2017.2)
Requires-Dist: requests (==2.13.0)
Requires-Dist: setuptools (==35.0.1)
Requires-Dist: six (==1.10.0)
Requires-Dist: smmap2 (==2.0.1)
Requires-Dist: Unidecode (==0.4.20)
Requires-Dist: Werkzeug (==0.12.1)
